whats_this_payload/__about__.py
whats_this_payload/__init__.py
whats_this_payload/exceptions.py
whats_this_payload/factory.py
whats_this_payload/py.typed
whats_this_payload/typing.py
whats_this_payload/utils.py
whats_this_payload/base/__init__.py
whats_this_payload/base/handler.py
whats_this_payload/base/identifier.py
whats_this_payload/base/payload_type.py
whats_this_payload/whatsapp/__init__.py
whats_this_payload/whatsapp/enums.py
whats_this_payload/whatsapp/handlers.py
whats_this_payload/whatsapp/identifier.py
whats_this_payload-1.2.4.dist-info/METADATA
whats_this_payload-1.2.4.dist-info/WHEEL
whats_this_payload-1.2.4.dist-info/licenses/LICENSE.txt
whats_this_payload-1.2.4.dist-info/RECORD
