Metadata-Version: 2.1
Name: whats_this_payload
Version: 1.2.4
Summary: Easily identify payload message type from popular webhooks
Project-URL: Documentation, https://github.com/Tomperez98/whats-this-payload#readme
Project-URL: Issues, https://github.com/Tomperez98/whats-this-payload/issues
Project-URL: Source, https://github.com/Tomperez98/whats-this-payload
Author-email: Tomas Perez Alvarez <tomasperezalvarez@gmail.com>
License-Expression: MIT
License-File: LICENSE.txt
Classifier: Development Status :: 4 - Beta
Classifier: Programming Language :: Python
Classifier: Programming Language :: Python :: 3.9
Classifier: Programming Language :: Python :: 3.10
Classifier: Programming Language :: Python :: 3.11
Classifier: Programming Language :: Python :: Implementation :: CPython
Classifier: Programming Language :: Python :: Implementation :: PyPy
Requires-Python: >=3.9
Provides-Extra: dev
Requires-Dist: black; extra == 'dev'
Requires-Dist: hatch; extra == 'dev'
Requires-Dist: mkdocs-material; extra == 'dev'
Requires-Dist: mypy; extra == 'dev'
Requires-Dist: pip-tools; extra == 'dev'
Requires-Dist: pytest; extra == 'dev'
Requires-Dist: pytest-cov; extra == 'dev'
Requires-Dist: ruff; extra == 'dev'
